a2a_cli/__init__.py
a2a_cli/a2a_client.py
a2a_cli/cli.py
a2a_cli/chat/__init__.py
a2a_cli/chat/chat_context.py
a2a_cli/chat/chat_handler.py
a2a_cli/chat/command_completer.py
a2a_cli/chat/ui_manager.py
a2a_cli/chat/commands/__init__.py
a2a_cli/chat/commands/agent.py
a2a_cli/chat/commands/artifacts.py
a2a_cli/chat/commands/connection.py
a2a_cli/chat/commands/debug.py
a2a_cli/chat/commands/help.py
a2a_cli/chat/commands/server.py
a2a_cli/chat/commands/tasks.py
a2a_cli/chat/commands/utility.py
a2a_cli/transport/__init__.py
a2a_cli/transport/http.py
a2a_cli/transport/sse.py
a2a_cli/transport/stdio.py
a2a_cli/transport/websocket.py
a2a_cli/ui/__init__.py
a2a_cli/ui/ansi_preview.py
a2a_cli/ui/colors.py
a2a_cli/ui/ui_helpers.py
a2a_cli-0.2.dist-info/licenses/LICENSE.md
a2a_cli-0.2.dist-info/METADATA
a2a_cli-0.2.dist-info/WHEEL
a2a_cli-0.2.dist-info/entry_points.txt
a2a_cli-0.2.dist-info/top_level.txt
a2a_cli-0.2.dist-info/RECORD
