Metadata-Version: 2.4
Name: a2a-cli
Version: 0.2
Summary: Command-line client for the A2A (Agent-to-Agent) Protocol
Author-email: Chris Hay <your.email@example.com>
License: MIT
Classifier: Development Status :: 4 - Beta
Classifier: Intended Audience :: Developers
Classifier: License :: OSI Approved :: MIT License
Classifier: Programming Language :: Python :: 3
Classifier: Programming Language :: Python :: 3.11
Classifier: Topic :: Software Development :: Libraries
Requires-Python: >=3.11
License-File: LICENSE.md
Requires-Dist: a2a-json-rpc>=0.3
Requires-Dist: httpx>=0.28.1
Requires-Dist: pillow>=11.2.1
Requires-Dist: prompt-toolkit>=3.0.51
Requires-Dist: rich>=14.0.0
Requires-Dist: typer>=0.15.2
Provides-Extra: dev
Requires-Dist: anyio>=4.9.0; extra == "dev"
Requires-Dist: pytest-asyncio>=0.26.0; extra == "dev"
Requires-Dist: pytest>=8.3.5; extra == "dev"
Dynamic: license-file
